niltechArduino/Arduino.py
niltechArduino/__init__.py
niltechArduino-1.0.6.dist-info/DESCRIPTION.rst
niltechArduino-1.0.6.dist-info/METADATA
niltechArduino-1.0.6.dist-info/RECORD
niltechArduino-1.0.6.dist-info/WHEEL
niltechArduino-1.0.6.dist-info/metadata.json
niltechArduino-1.0.6.dist-info/top_level.txt
