Metadata-Version: 2.0
Name: niltechArduino
Version: 1.0.6
Summary: A lib to automatically detect and give usb port which is connected to arduino and also extract incoming data using start and stop bytes
Home-page: UNKNOWN
Author: Vaibhav VK - Niltech
Author-email: vaibhav@niltech.in
License: UNKNOWN
Keywords: Arduino,getPort,readData,extractData
Platform: UNKNOWN
